skyline/__init__.py
skyline/__main__.py
skyline/error_printing.py
skyline/evaluate.py
skyline/exceptions.py
skyline/initialization.py
skyline/lru_cache.py
skyline/nvml.py
skyline/server.py
skyline/user_code_utils.py
skyline/version_utils.py
skyline/analysis/__init__.py
skyline/analysis/request_manager.py
skyline/analysis/runner.py
skyline/analysis/session.py
skyline/analysis/static.py
skyline/commands/__init__.py
skyline/commands/interactive.py
skyline/commands/measurements.py
skyline/commands/memory.py
skyline/commands/prediction_models.py
skyline/commands/time.py
skyline/config/__init__.py
skyline/data/__init__.py
skyline/data/hints.yml
skyline/io/__init__.py
skyline/io/connection.py
skyline/io/connection_acceptor.py
skyline/io/connection_manager.py
skyline/io/sentinel.py
skyline/models/__init__.py
skyline/models/analysis.py
skyline/models/source_map.py
skyline/profiler/__init__.py
skyline/profiler/autograd.py
skyline/profiler/backward.py
skyline/profiler/iteration.py
skyline/profiler/operation.py
skyline/protocol/__init__.py
skyline/protocol/message_handler.py
skyline/protocol/message_sender.py
skyline/protocol_gen/__init__.py
skyline/protocol_gen/innpv_pb2.py
skyline/tests/__init__.py
skyline/tests/test_lru_cache.py
skyline/tracking/__init__.py
skyline/tracking/backward_interceptor.py
skyline/tracking/base.py
skyline/tracking/breakdown.py
skyline/tracking/call_stack.py
skyline/tracking/callable_tracker.py
skyline/tracking/hook_manager.py
skyline/tracking/tracker.py
skyline/tracking/utils.py
skyline/tracking/memory/__init__.py
skyline/tracking/memory/activations.py
skyline/tracking/memory/report.py
skyline/tracking/memory/report_queries.py
skyline/tracking/memory/weights.py
skyline/tracking/time/__init__.py
skyline/tracking/time/operation.py
skyline/tracking/time/report.py
skyline/tracking/time/report_queries.py
skyline_cli-0.5.0.dist-info/METADATA
skyline_cli-0.5.0.dist-info/WHEEL
skyline_cli-0.5.0.dist-info/entry_points.txt
skyline_cli-0.5.0.dist-info/top_level.txt
skyline_cli-0.5.0.dist-info/RECORD
